kvm_serial/__init__.py
kvm_serial/__main__.py
kvm_serial/control.py
kvm_serial/kvm.py
kvm_serial/backend/__init__.py
kvm_serial/backend/inputhandler.py
kvm_serial/backend/keyboard.py
kvm_serial/backend/mouse.py
kvm_serial/backend/video.py
kvm_serial/backend/implementations/__init__.py
kvm_serial/backend/implementations/baseop.py
kvm_serial/backend/implementations/cursesop.py
kvm_serial/backend/implementations/mouseop.py
kvm_serial/backend/implementations/pynputop.py
kvm_serial/backend/implementations/pyusbop.py
kvm_serial/backend/implementations/qtop.py
kvm_serial/backend/implementations/ttyop.py
kvm_serial/utils/__init__.py
kvm_serial/utils/communication.py
kvm_serial/utils/keyboard_layouts.py
kvm_serial/utils/settings.py
kvm_serial/utils/utils.py
kvm_serial-1.5.3.dist-info/licenses/LICENSE.md
kvm_serial-1.5.3.dist-info/METADATA
kvm_serial-1.5.3.dist-info/WHEEL
kvm_serial-1.5.3.dist-info/entry_points.txt
kvm_serial-1.5.3.dist-info/top_level.txt
kvm_serial-1.5.3.dist-info/RECORD
