Metadata-Version: 2.4
Name: kvm-serial
Version: 1.5.3
Summary: Python package for interfacing with CH9329 KVM devices
Author-email: Samantha Finnigan <1038320+sjmf@users.noreply.github.com>
License-Expression: MIT
Project-URL: Homepage, https://github.com/sjmf/kvm-serial
Project-URL: Issues, https://github.com/sjmf/kvm-serial/issues
Classifier: Programming Language :: Python :: 3
Classifier: Operating System :: OS Independent
Requires-Python: >=3.10
License-File: LICENSE.md
Requires-Dist: pyserial>=3.5
Requires-Dist: pyusb>=1.3.1
Requires-Dist: pynput>=1.8.1
Requires-Dist: opencv-python>=4.11.0.0
Requires-Dist: screeninfo>=0.6.7
Requires-Dist: pyqt5>=5.15.11
Requires-Dist: toml>=0.10.2
Provides-Extra: dev
Requires-Dist: pytest; extra == "dev"
Requires-Dist: pytest-cov; extra == "dev"
Requires-Dist: pytest-watch; extra == "dev"
Requires-Dist: pytest-timeout; extra == "dev"
Requires-Dist: black==26.1.0; extra == "dev"
Requires-Dist: pre-commit; extra == "dev"
Requires-Dist: pyinstaller>=6.0; extra == "dev"
Dynamic: license-file
